pysdb/__init__.py
pysdb-0.0.3.dist-info/METADATA
pysdb-0.0.3.dist-info/RECORD
pysdb-0.0.3.dist-info/WHEEL
pysdb-0.0.3.dist-info/top_level.txt
