Metadata-Version: 2.1
Name: pysdb
Version: 0.0.3
Summary: A simple lightweight portable, embeddable database library
Home-page: https://github.com/TheSyedAasif/pysdb
Author: Syed Aasif
Author-email: thesyedaasif@hotmail.com
License: UNKNOWN
Platform: UNKNOWN
Classifier: Programming Language :: Python :: 3
Classifier: License :: OSI Approved :: Mozilla Public License 2.0 (MPL 2.0)
Classifier: Operating System :: OS Independent
